citree/__init__.py
citree/main.py
citree-0.0.7.dist-info/METADATA
citree-0.0.7.dist-info/WHEEL
citree-0.0.7.dist-info/top_level.txt
citree-0.0.7.dist-info/RECORD
