Metadata-Version: 2.1
Name: citree
Version: 0.0.7
Summary: creates citation tree plot using DOI
Home-page: https://github.com/igormintz/Citree
Author: Igor Mintz
Author-email: igormintz@gmail.com
License: UNKNOWN
Platform: UNKNOWN
Classifier: Programming Language :: Python :: 3
Classifier: License :: OSI Approved :: MIT License
Classifier: Operating System :: OS Independent
Requires-Python: >=3.6
